shado.cpython-310-x86_64-linux-gnu.so
shado-0.0.10.dist-info/RECORD
shado-0.0.10.dist-info/METADATA
shado-0.0.10.dist-info/WHEEL
shado-0.0.10.dist-info/top_level.txt
